data/tos.jsonl
weboptout/__init__.py
weboptout/__main__.py
weboptout/client.py
weboptout/config.py
weboptout/html.py
weboptout/http.py
weboptout/steps.py
weboptout/types.py
weboptout/utils.py
weboptout/web.py
weboptout-0.3.2.dist-info/LICENSE
weboptout-0.3.2.dist-info/METADATA
weboptout-0.3.2.dist-info/WHEEL
weboptout-0.3.2.dist-info/entry_points.txt
weboptout-0.3.2.dist-info/RECORD
